spongebobsay/VERSION
spongebobsay/__init__.py
spongebobsay/__main__.py
spongebobsay/spongebobsay.py
spongebobsay-0.4.1.dist-info/LICENSE
spongebobsay-0.4.1.dist-info/METADATA
spongebobsay-0.4.1.dist-info/WHEEL
spongebobsay-0.4.1.dist-info/entry_points.txt
spongebobsay-0.4.1.dist-info/top_level.txt
spongebobsay-0.4.1.dist-info/RECORD
