Metadata-Version: 2.1
Name: spongebobsay
Version: 0.4.1
Summary: AScIi MOcKiNg sPONgEbOB comMAnD-lIne ProGrAm
Home-page: https://github.com/jayqi/spongebob
Author: Jay Qi
Author-email: jayqi.opensource@gmail.com
License: UNKNOWN
Keywords: mocking spongebob case,spongebob,spongebob case,spongebobsay
Platform: UNKNOWN
Classifier: Programming Language :: Python :: 3
Classifier: License :: OSI Approved :: BSD License
Classifier: Operating System :: OS Independent
Classifier: Topic :: Text Processing
Classifier: Topic :: Utilities
Requires-Python: >=3.6
Requires-Dist: typer (>=0.3.0)
Requires-Dist: spongebobcase (<0.5.0,>=0.4.0)
